mcp_server_evefleet/__init__.py
mcp_server_evefleet/config.yaml
mcp_server_evefleet/config_load.py
mcp_server_evefleet/functions.py
mcp_server_evefleet/server.py
mcp_server_evefleet/static_manage.py
mcp_server_evefleet/IO/API_IO.py
mcp_server_evefleet/IO/__init__.py
mcp_server_evefleet/IO/fleet_api.py
mcp_server_evefleet/setting/chardict.yaml
mcp_server_evefleet/setting/shipid_list.csv
mcp_server_evefleet/setting/static.yaml
mcp_server_evefleet/setting/system.yaml
mcp_server_evefleet/sso/__init__.py
mcp_server_evefleet/sso/revoke_refresh_token.py
mcp_server_evefleet/sso/shared_flow.py
mcp_server_evefleet/sso/validate_jwt.py
mcp_server_evefleet-0.1.5.dist-info/licenses/LICENSE
mcp_server_evefleet-0.1.5.dist-info/METADATA
mcp_server_evefleet-0.1.5.dist-info/WHEEL
mcp_server_evefleet-0.1.5.dist-info/top_level.txt
mcp_server_evefleet-0.1.5.dist-info/RECORD
