Metadata-Version: 2.4
Name: mcp-server-evefleet
Version: 0.1.5
Summary: Add your description here
Requires-Python: >=3.12
License-File: LICENSE
Requires-Dist: aiohttp==3.12.15
Requires-Dist: anyio>=4.0.0
Requires-Dist: certifi>=2024.12.14
Requires-Dist: charset-normalizer>=3.0.0
Requires-Dist: ecdsa==0.19.0
Requires-Dist: idna>=3.7
Requires-Dist: mcp[cli]>=1.14.0
Requires-Dist: pyasn1==0.4.8
Requires-Dist: python-jose==3.3.0
Requires-Dist: pyyaml==6.0.1
Requires-Dist: requests==2.32.3
Requires-Dist: rsa==4.9
Requires-Dist: six==1.16.0
Requires-Dist: sniffio>=1.0.0
Requires-Dist: urllib3>=2.2.0
Requires-Dist: platformdirs>=4.2.2
Dynamic: license-file
